ainewt_mongo/__init__.py
ainewt_mongo/mongo.py
mongodb/__init__.py
mongodb/mongo.py
ainewt_mongo-0.1.0.dist-info/METADATA
ainewt_mongo-0.1.0.dist-info/WHEEL
ainewt_mongo-0.1.0.dist-info/top_level.txt
ainewt_mongo-0.1.0.dist-info/RECORD
