Metadata-Version: 2.1
Name: ainewt-mongo
Version: 0.1.0
Summary: A MongoDB utility package
Home-page: https://your.package.repo.url
Author: Your Name
Author-email: your.email@example.com
Classifier: Programming Language :: Python :: 3
Classifier: License :: OSI Approved :: MIT License
Classifier: Operating System :: OS Independent
Requires-Python: >=3.6
Requires-Dist: pymongo
Requires-Dist: bson
